{"doctype":"markdown","bookId":"book:LP2seisLU","createdAt":1673896355826,"updatedAt":1689710313382,"status":"none","share":"private","numOfTasks":0,"numOfCheckedTasks":0,"title":"Creds","body":"\n\n\n\nFr1d4y%50on!\n\npre-preprod\nprebesyssicssrvPre\n44Z[_LRiL8[wn]s!k]a%48\n\ntest-preprod\nprebesyssicssrvTst\nAkljmlkujw9l400$$100Whlih\n\nprod\nprebesyssicssrv\nR9DU_5uxjSR[H5tU<4Csvp\n\nPreHReptSrv\nUedksowehj56d0@\n\n\n\nhttps://partnerre1.sharepoint.com/sites/GlobalActuarial/Shared%20Documents/Forms/AllItems.aspx?csf=1&web=1&e=ZazFBL&OR=Teams%2DHL&CT=1684309367083&clickparams=eyJBcHBOYW1lIjoiVGVhbXMtRGVza3RvcCIsIkFwcFZlcnNpb24iOiIyNy8yMzA0MDIwMjcwNSIsIkhhc0ZlZGVyYXRlZFVzZXIiOmZhbHNlfQ%3D%3D&cid=6e2a9dcd%2D04c5%2D4847%2Dbda0%2De3c3a29df7ef&FolderCTID=0x012000BCBF6754D9F223428ACC33509EEA7E6F&id=%2Fsites%2FGlobalActuarial%2FShared%20Documents%2FGA%2FDept%5FLevel%2FRenewals%2FRisk%20Transfer%2FRisk%20Transfer%202022&viewid=5c80ffe6%2Da07c%2D4044%2Db16b%2D831ac0fab39b","tags":[],"_id":"note:Mdm4-GvJZ","_rev":"21-1546125a36ed156e654737d2d9d64b14"}